stock_market-0.4.1-py3.6-nspkg.pth
stock_market/_version.backup.py
stock_market/_version.py
stock_market/analytics/__init__.py
stock_market/analytics/fiavestXT/__init__.py
stock_market/analytics/fiavestXT/main.py
stock_market/screeners/__init__.py
stock_market/screeners/bursamalaysia/__init__.py
stock_market/screeners/bursamalaysia/api.py
stock_market/screeners/bursamalaysia/securities_equities.py
stock_market/screeners/i3investor/__init__.py
stock_market/screeners/i3investor/api.py
stock_market/screeners/klsescreener/__init__.py
stock_market/screeners/klsescreener/api.py
stock_market/trading_platform/__init__.py
stock_market/trading_platform/mplus/__init__.py
stock_market/trading_platform/mplus/beautiful.py
stock_market/utility/__init__.py
stock_market/utility/malaysia/__init__.py
stock_market/utility/malaysia/bid_change.py
stock_market/utility/malaysia/stamp_duty_exception.py
stock_market-0.4.1.dist-info/LICENSE
stock_market-0.4.1.dist-info/METADATA
stock_market-0.4.1.dist-info/WHEEL
stock_market-0.4.1.dist-info/namespace_packages.txt
stock_market-0.4.1.dist-info/top_level.txt
stock_market-0.4.1.dist-info/RECORD
