Metadata-Version: 2.1
Name: stock-market
Version: 0.4.1
Summary: A library that gather stock market historical OHLC data.
Home-page: https://github.com/kimkeatc/stock-market
Author: kimkeatc
Author-email: kim.keat.chin@outlook.com
Maintainer: kimkeatc
Maintainer-email: kim.keat.chin@outlook.com
License: MIT
Keywords: klsescreener
Platform: any
Classifier: Development Status :: 1 - Planning
Classifier: License :: OSI Approved :: MIT License
Classifier: Operating System :: Microsoft :: Windows
Classifier: Programming Language :: Python :: 3
Requires-Python: >=3.6
Requires-Dist: bs4
Requires-Dist: html5lib
Requires-Dist: pandas
Requires-Dist: requests
Requires-Dist: wheel
Provides-Extra: dev
Requires-Dist: pytest ; extra == 'dev'
Requires-Dist: pytest-reportlog ; extra == 'dev'
